nano_banana_1/__init__.py
nano_banana_1-1766993.9.7.dist-info/licenses/LICENSE
nano_banana_1-1766993.9.7.dist-info/METADATA
nano_banana_1-1766993.9.7.dist-info/WHEEL
nano_banana_1-1766993.9.7.dist-info/top_level.txt
nano_banana_1-1766993.9.7.dist-info/RECORD
