Metadata-Version: 2.4
Name: nano-banana-1
Version: 1766993.9.7
Summary: High-quality integration for https://supermaker.ai/image/nano-banana/
Home-page: https://supermaker.ai/image/nano-banana/
Author: SuperMaker
Classifier: Programming Language :: Python :: 3
Classifier: License :: OSI Approved :: MIT License
Requires-Python: >=3.6
License-File: LICENSE
Dynamic: author
Dynamic: classifier
Dynamic: description
Dynamic: description-content-type
Dynamic: home-page
Dynamic: license-file
Dynamic: requires-python
Dynamic: summary
